[
   {
        "id": 453754,
        "name": "Valmiera",
        "state": "",
        "country": "LV",
        "coord": {
            "lon": 25.427509,
            "lat": 57.54108
        }
    },
    {
        "id": 453850,
        "name": "Zilupe",
        "state": "",
        "country": "LV",
        "coord": {
            "lon": 28.121651,
            "lat": 56.386162
        }
    },
    {
        "id": 454078,
        "name": "Višķi",
        "state": "",
        "country": "LV",
        "coord": {
            "lon": 26.783211,
            "lat": 56.05344
        }
    },
    {
        "id": 454130,
        "name": "Viļaka",
        "state": "",
        "country": "LV",
        "coord": {
            "lon": 27.672199,
            "lat": 57.184582
        }
    },
    {
        "id": 454166,
        "name": "Vilcēņi",
        "state": "",
        "country": "LV",
        "coord": {
            "lon": 24.0,
            "lat": 56.566669
        }
    },
    {
        "id": 454178,
        "name": "Viļāni",
        "state": "",
        "country": "LV",
        "coord": {
            "lon": 26.92449,
            "lat": 56.552528
        }
    },
    {
        "id": 454216,
        "name": "Viesīte",
        "state": "",
        "country": "LV",
        "coord": {
            "lon": 25.55514,
            "lat": 56.347511
        }
    },
    {
        "id": 454273,
        "name": "Vecumnieki",
        "state": "",
        "country": "LV",
        "coord": {
            "lon": 24.522221,
            "lat": 56.606392
        }
    },
    {
        "id": 454307,
        "name": "Ventspils Municipality",
        "state": "",
        "country": "LV",
        "coord": {
            "lon": 21.83333,
            "lat": 57.333328
        }
    },
    {
        "id": 454310,
        "name": "Ventspils",
        "state": "",
        "country": "LV",
        "coord": {
            "lon": 21.56056,
            "lat": 57.389439
        }
    },
    {
        "id": 454372,
        "name": "Vecvārkava",
        "state": "",
        "country": "LV",
        "coord": {
            "lon": 26.51667,
            "lat": 56.183331
        }
    },
    {
        "id": 454407,
        "name": "Vecpils",
        "state": "",
        "country": "LV",
        "coord": {
            "lon": 21.48333,
            "lat": 56.633331
        }
    },
    {
        "id": 454432,
        "name": "Vec-Liepāja",
        "state": "",
        "country": "LV",
        "coord": {
            "lon": 21.01667,
            "lat": 56.533329
        }
    },
    {
        "id": 454436,
        "name": "Veckrogi",
        "state": "",
        "country": "LV",
        "coord": {
            "lon": 22.0,
            "lat": 56.966671
        }
    },
    {
        "id": 454468,
        "name": "Vecauce",
        "state": "",
        "country": "LV",
        "coord": {
            "lon": 22.889669,
            "lat": 56.468369
        }
    },
    {
        "id": 454537,
        "name": "Vangaži",
        "state": "",
        "country": "LV",
        "coord": {
            "lon": 24.548611,
            "lat": 57.093609
        }
    },
    {
        "id": 454564,
        "name": "Valmiera",
        "state": "",
        "country": "LV",
        "coord": {
            "lon": 25.25,
            "lat": 57.75
        }
    },
    {
        "id": 454571,
        "name": "Valka Municipality",
        "state": "",
        "country": "LV",
        "coord": {
            "lon": 25.91667,
            "lat": 57.583328
        }
    },
    {
        "id": 454572,
        "name": "Valka",
        "state": "",
        "country": "LV",
        "coord": {
            "lon": 26.01013,
            "lat": 57.7752
        }
    },
    {
        "id": 454584,
        "name": "Valdemārpils",
        "state": "",
        "country": "LV",
        "coord": {
            "lon": 22.591881,
            "lat": 57.370682
        }
    },
    {
        "id": 454602,
        "name": "Vaiņode",
        "state": "",
        "country": "LV",
        "coord": {
            "lon": 21.866671,
            "lat": 56.433331
        }
    },
    {
        "id": 454714,
        "name": "Ulbroka",
        "state": "",
        "country": "LV",
        "coord": {
            "lon": 24.289721,
            "lat": 56.941109
        }
    },
    {
        "id": 454726,
        "name": "Ūdriņi",
        "state": "",
        "country": "LV",
        "coord": {
            "lon": 25.678141,
            "lat": 57.616589
        }
    },
    {
        "id": 454768,
        "name": "Tukums",
        "state": "",
        "country": "LV",
        "coord": {
            "lon": 23.155279,
            "lat": 56.966942
        }
    },
    {
        "id": 454771,
        "name": "Tukuma novads",
        "state": "",
        "country": "LV",
        "coord": {
            "lon": 23.0,
            "lat": 56.916672
        }
    },
    {
        "id": 454810,
        "name": "Torņakalns",
        "state": "",
        "country": "LV",
        "coord": {
            "lon": 24.09111,
            "lat": 56.927776
        }
    },
    {
        "id": 454848,
        "name": "Tīreļi",
        "state": "",
        "country": "LV",
        "coord": {
            "lon": 23.58902,
            "lat": 56.839909
        }
    },
    {
        "id": 454968,
        "name": "Talsi Municipality",
        "state": "",
        "country": "LV",
        "coord": {
            "lon": 22.58333,
            "lat": 57.333328
        }
    },
    {
        "id": 454970,
        "name": "Talsi",
        "state": "",
        "country": "LV",
        "coord": {
            "lon": 22.581369,
            "lat": 57.245621
        }
    },
    {
        "id": 455102,
        "name": "Subate",
        "state": "",
        "country": "LV",
        "coord": {
            "lon": 25.90756,
            "lat": 56.006199
        }
    },
    {
        "id": 455166,
        "name": "Strenči",
        "state": "",
        "country": "LV",
        "coord": {
            "lon": 25.68535,
            "lat": 57.62574
        }
    },
    {
        "id": 455260,
        "name": "Stende",
        "state": "",
        "country": "LV",
        "coord": {
            "lon": 22.533331,
            "lat": 57.150002
        }
    },
    {
        "id": 455298,
        "name": "Staicele",
        "state": "",
        "country": "LV",
        "coord": {
            "lon": 24.75,
            "lat": 57.836391
        }
    },
    {
        "id": 455372,
        "name": "Somerseta",
        "state": "",
        "country": "LV",
        "coord": {
            "lon": 27.01667,
            "lat": 56.133331
        }
    },
    {
        "id": 455406,
        "name": "Smiltene",
        "state": "",
        "country": "LV",
        "coord": {
            "lon": 25.90164,
            "lat": 57.424438
        }
    },
    {
        "id": 455499,
        "name": "Skulte",
        "state": "",
        "country": "LV",
        "coord": {
            "lon": 23.953329,
            "lat": 56.919441
        }
    },
    {
        "id": 455520,
        "name": "Skrunda",
        "state": "",
        "country": "LV",
        "coord": {
            "lon": 22.01667,
            "lat": 56.683331
        }
    },
    {
        "id": 455718,
        "name": "Sigulda",
        "state": "",
        "country": "LV",
        "coord": {
            "lon": 24.864719,
            "lat": 57.151939
        }
    },
    {
        "id": 455727,
        "name": "Sidgunda",
        "state": "",
        "country": "LV",
        "coord": {
            "lon": 24.9175,
            "lat": 56.96167
        }
    },
    {
        "id": 455786,
        "name": "Seda",
        "state": "",
        "country": "LV",
        "coord": {
            "lon": 25.75,
            "lat": 57.650002
        }
    },
    {
        "id": 455812,
        "name": "Saulkrasti",
        "state": "",
        "country": "LV",
        "coord": {
            "lon": 24.414709,
            "lat": 57.262241
        }
    },
    {
        "id": 455888,
        "name": "Saldus Municipality",
        "state": "",
        "country": "LV",
        "coord": {
            "lon": 22.5,
            "lat": 56.666672
        }
    },
    {
        "id": 455890,
        "name": "Saldus",
        "state": "",
        "country": "LV",
        "coord": {
            "lon": 22.48807,
            "lat": 56.663631
        }
    },
    {
        "id": 455898,
        "name": "Salaspils",
        "state": "",
        "country": "LV",
        "coord": {
            "lon": 24.36544,
            "lat": 56.860142
        }
    },
    {
        "id": 455910,
        "name": "Salacgrīva",
        "state": "",
        "country": "LV",
        "coord": {
            "lon": 24.358061,
            "lat": 57.753609
        }
    },
    {
        "id": 455937,
        "name": "Sabile",
        "state": "",
        "country": "LV",
        "coord": {
            "lon": 22.572611,
            "lat": 57.045769
        }
    },
    {
        "id": 456008,
        "name": "Rūjiena",
        "state": "",
        "country": "LV",
        "coord": {
            "lon": 25.331551,
            "lat": 57.897518
        }
    },
    {
        "id": 456015,
        "name": "Rugāji",
        "state": "",
        "country": "LV",
        "coord": {
            "lon": 27.133329,
            "lat": 57.0
        }
    },
    {
        "id": 456090,
        "name": "Ropaži",
        "state": "",
        "country": "LV",
        "coord": {
            "lon": 24.63361,
            "lat": 56.973888
        }
    },
    {
        "id": 456107,
        "name": "Roja",
        "state": "",
        "country": "LV",
        "coord": {
            "lon": 22.816669,
            "lat": 57.5
        }
    },
    {
        "id": 456169,
        "name": "Rīgas Rajons",
        "state": "",
        "country": "LV",
        "coord": {
            "lon": 24.333332,
            "lat": 57.0
        }
    },
    {
        "id": 456172,
        "name": "Riga",
        "state": "",
        "country": "LV",
        "coord": {
            "lon": 24.1,
            "lat": 56.950001
        }
    },
    {
        "id": 456173,
        "name": "Rīga",
        "state": "",
        "country": "LV",
        "coord": {
            "lon": 24.083332,
            "lat": 57.0
        }
    },
    {
        "id": 456197,
        "name": "Rēzeknes Novads",
        "state": "",
        "country": "LV",
        "coord": {
            "lon": 27.16667,
            "lat": 56.5
        }
    },
    {
        "id": 456202,
        "name": "Rēzekne",
        "state": "",
        "country": "LV",
        "coord": {
            "lon": 27.316669,
            "lat": 56.5
        }
    },
    {
        "id": 456506,
        "name": "Priekule",
        "state": "",
        "country": "LV",
        "coord": {
            "lon": 21.58968,
            "lat": 56.446789
        }
    },
    {
        "id": 456528,
        "name": "Preiļi Municipality",
        "state": "",
        "country": "LV",
        "coord": {
            "lon": 26.66667,
            "lat": 56.333328
        }
    },
    {
        "id": 456530,
        "name": "Preiļi",
        "state": "",
        "country": "LV",
        "coord": {
            "lon": 26.72459,
            "lat": 56.294441
        }
    },
    {
        "id": 456630,
        "name": "Pļavnieki",
        "state": "",
        "country": "LV",
        "coord": {
            "lon": 24.208332,
            "lat": 56.939167
        }
    },
    {
        "id": 456635,
        "name": "Pļaviņas",
        "state": "",
        "country": "LV",
        "coord": {
            "lon": 25.725519,
            "lat": 56.617802
        }
    },
    {
        "id": 456685,
        "name": "Piņķi",
        "state": "",
        "country": "LV",
        "coord": {
            "lon": 23.91083,
            "lat": 56.94194
        }
    },
    {
        "id": 456696,
        "name": "Piltene",
        "state": "",
        "country": "LV",
        "coord": {
            "lon": 21.674391,
            "lat": 57.224258
        }
    },
    {
        "id": 456698,
        "name": "Pilsrundāle",
        "state": "",
        "country": "LV",
        "coord": {
            "lon": 24.0,
            "lat": 56.416672
        }
    },
    {
        "id": 456827,
        "name": "Pāvilosta",
        "state": "",
        "country": "LV",
        "coord": {
            "lon": 21.18593,
            "lat": 56.887909
        }
    },
    {
        "id": 456954,
        "name": "Ozolnieki",
        "state": "",
        "country": "LV",
        "coord": {
            "lon": 23.787781,
            "lat": 56.68639
        }
    },
    {
        "id": 457052,
        "name": "Olaine",
        "state": "",
        "country": "LV",
        "coord": {
            "lon": 23.938061,
            "lat": 56.785278
        }
    },
    {
        "id": 457061,
        "name": "Ogres novads",
        "state": "",
        "country": "LV",
        "coord": {
            "lon": 25.0,
            "lat": 56.75
        }
    },
    {
        "id": 457065,
        "name": "Ogre",
        "state": "",
        "country": "LV",
        "coord": {
            "lon": 24.61401,
            "lat": 56.8162
        }
    },
    {
        "id": 457138,
        "name": "Nida",
        "state": "",
        "country": "LV",
        "coord": {
            "lon": 21.066669,
            "lat": 56.099998
        }
    },
    {
        "id": 457211,
        "name": "Mūrmuiža",
        "state": "",
        "country": "LV",
        "coord": {
            "lon": 25.48333,
            "lat": 57.48333
        }
    },
    {
        "id": 457408,
        "name": "Mērsrags",
        "state": "",
        "country": "LV",
        "coord": {
            "lon": 23.12455,
            "lat": 57.33535
        }
    },
    {
        "id": 457533,
        "name": "Mazsalaca",
        "state": "",
        "country": "LV",
        "coord": {
            "lon": 25.05475,
            "lat": 57.863289
        }
    },
    {
        "id": 457676,
        "name": "Mālpils",
        "state": "",
        "country": "LV",
        "coord": {
            "lon": 24.96306,
            "lat": 57.011108
        }
    },
    {
        "id": 457712,
        "name": "Madona Municipality",
        "state": "",
        "country": "LV",
        "coord": {
            "lon": 26.25,
            "lat": 56.833328
        }
    },
    {
        "id": 457714,
        "name": "Madona",
        "state": "",
        "country": "LV",
        "coord": {
            "lon": 26.21698,
            "lat": 56.853291
        }
    },
    {
        "id": 457742,
        "name": "Ļurbava",
        "state": "",
        "country": "LV",
        "coord": {
            "lon": 27.66486,
            "lat": 56.781792
        }
    },
    {
        "id": 457773,
        "name": "Ludzas novads",
        "state": "",
        "country": "LV",
        "coord": {
            "lon": 27.75,
            "lat": 56.5
        }
    },
    {
        "id": 457776,
        "name": "Ludza",
        "state": "",
        "country": "LV",
        "coord": {
            "lon": 27.716669,
            "lat": 56.549999
        }
    },
    {
        "id": 457799,
        "name": "Lubāna",
        "state": "",
        "country": "LV",
        "coord": {
            "lon": 26.716669,
            "lat": 56.900002
        }
    },
    {
        "id": 457822,
        "name": "Loja",
        "state": "",
        "country": "LV",
        "coord": {
            "lon": 24.64444,
            "lat": 57.154442
        }
    },
    {
        "id": 457860,
        "name": "Līvāni",
        "state": "",
        "country": "LV",
        "coord": {
            "lon": 26.175791,
            "lat": 56.354309
        }
    },
    {
        "id": 457889,
        "name": "Limbažu novads",
        "state": "",
        "country": "LV",
        "coord": {
            "lon": 24.66667,
            "lat": 57.583328
        }
    },
    {
        "id": 457890,
        "name": "Limbaži",
        "state": "",
        "country": "LV",
        "coord": {
            "lon": 24.71941,
            "lat": 57.512871
        }
    },
    {
        "id": 457912,
        "name": "Līgatne",
        "state": "",
        "country": "LV",
        "coord": {
            "lon": 25.04059,
            "lat": 57.234291
        }
    },
    {
        "id": 457951,
        "name": "Liepājas Rajons",
        "state": "",
        "country": "LV",
        "coord": {
            "lon": 21.41667,
            "lat": 56.5
        }
    },
    {
        "id": 457954,
        "name": "Liepāja",
        "state": "",
        "country": "LV",
        "coord": {
            "lon": 21.01667,
            "lat": 56.51667
        }
    },
    {
        "id": 457955,
        "name": "Liepāja",
        "state": "",
        "country": "LV",
        "coord": {
            "lon": 21.036671,
            "lat": 56.541939
        }
    },
    {
        "id": 457965,
        "name": "Lielvārde",
        "state": "",
        "country": "LV",
        "coord": {
            "lon": 24.80743,
            "lat": 56.720661
        }
    },
    {
        "id": 458065,
        "name": "Lieģi",
        "state": "",
        "country": "LV",
        "coord": {
            "lon": 21.33399,
            "lat": 56.58173
        }
    },
    {
        "id": 458151,
        "name": "Lejasciems",
        "state": "",
        "country": "LV",
        "coord": {
            "lon": 26.57679,
            "lat": 57.280251
        }
    },
    {
        "id": 458258,
        "name": "Republic of Latvia",
        "state": "",
        "country": "LV",
        "coord": {
            "lon": 25.0,
            "lat": 57.0
        }
    },
    {
        "id": 458459,
        "name": "Kuldīgas novads",
        "state": "",
        "country": "LV",
        "coord": {
            "lon": 22.0,
            "lat": 56.833328
        }
    },
    {
        "id": 458460,
        "name": "Kuldīga",
        "state": "",
        "country": "LV",
        "coord": {
            "lon": 21.957211,
            "lat": 56.973991
        }
    },
    {
        "id": 458621,
        "name": "Krāslavas novads",
        "state": "",
        "country": "LV",
        "coord": {
            "lon": 27.5,
            "lat": 56.083328
        }
    },
    {
        "id": 458623,
        "name": "Krāslava",
        "state": "",
        "country": "LV",
        "coord": {
            "lon": 27.16799,
            "lat": 55.895142
        }
    },
    {
        "id": 458682,
        "name": "Kolka",
        "state": "",
        "country": "LV",
        "coord": {
            "lon": 22.58333,
            "lat": 57.75
        }
    },
    {
        "id": 458687,
        "name": "Koknese",
        "state": "",
        "country": "LV",
        "coord": {
            "lon": 25.433331,
            "lat": 56.650002
        }
    },
    {
        "id": 458690,
        "name": "Kokari",
        "state": "",
        "country": "LV",
        "coord": {
            "lon": 26.735571,
            "lat": 56.61771
        }
    },
    {
        "id": 458774,
        "name": "Ķiviļi",
        "state": "",
        "country": "LV",
        "coord": {
            "lon": 21.183331,
            "lat": 56.549999
        }
    },
    {
        "id": 458880,
        "name": "Ķekava",
        "state": "",
        "country": "LV",
        "coord": {
            "lon": 24.23,
            "lat": 56.826618
        }
    },
    {
        "id": 458892,
        "name": "Ķegums",
        "state": "",
        "country": "LV",
        "coord": {
            "lon": 24.72439,
            "lat": 56.745098
        }
    },
    {
        "id": 458972,
        "name": "Kārsava",
        "state": "",
        "country": "LV",
        "coord": {
            "lon": 27.68829,
            "lat": 56.78405
        }
    },
    {
        "id": 459031,
        "name": "Kandava",
        "state": "",
        "country": "LV",
        "coord": {
            "lon": 22.77466,
            "lat": 57.040871
        }
    },
    {
        "id": 459072,
        "name": "Lācīši",
        "state": "",
        "country": "LV",
        "coord": {
            "lon": 26.283331,
            "lat": 55.966671
        }
    },
    {
        "id": 459102,
        "name": "Kalnciems",
        "state": "",
        "country": "LV",
        "coord": {
            "lon": 23.60972,
            "lat": 56.801109
        }
    },
    {
        "id": 459201,
        "name": "Jūrmala",
        "state": "",
        "country": "LV",
        "coord": {
            "lon": 23.77038,
            "lat": 56.967999
        }
    },
    {
        "id": 459202,
        "name": "Jūrmala",
        "state": "",
        "country": "LV",
        "coord": {
            "lon": 23.695311,
            "lat": 56.951981
        }
    },
    {
        "id": 459220,
        "name": "Jumprava",
        "state": "",
        "country": "LV",
        "coord": {
            "lon": 24.972099,
            "lat": 56.676128
        }
    },
    {
        "id": 459278,
        "name": "Jelgavas novads",
        "state": "",
        "country": "LV",
        "coord": {
            "lon": 23.75,
            "lat": 56.583328
        }
    },
    {
        "id": 459279,
        "name": "Jelgava",
        "state": "",
        "country": "LV",
        "coord": {
            "lon": 23.71278,
            "lat": 56.650002
        }
    },
    {
        "id": 459282,
        "name": "Jēkabpils Municipality",
        "state": "",
        "country": "LV",
        "coord": {
            "lon": 25.83333,
            "lat": 56.333328
        }
    },
    {
        "id": 459283,
        "name": "Jēkabpils",
        "state": "",
        "country": "LV",
        "coord": {
            "lon": 25.857349,
            "lat": 56.499031
        }
    },
    {
        "id": 459357,
        "name": "Jaunpils",
        "state": "",
        "country": "LV",
        "coord": {
            "lon": 23.013611,
            "lat": 56.732498
        }
    },
    {
        "id": 459359,
        "name": "Jaunpiebalga",
        "state": "",
        "country": "LV",
        "coord": {
            "lon": 26.049999,
            "lat": 57.183331
        }
    },
    {
        "id": 459402,
        "name": "Jaunjelgava",
        "state": "",
        "country": "LV",
        "coord": {
            "lon": 25.08333,
            "lat": 56.616669
        }
    },
    {
        "id": 459411,
        "name": "Jaundubulti",
        "state": "",
        "country": "LV",
        "coord": {
            "lon": 23.75,
            "lat": 56.964722
        }
    },
    {
        "id": 459419,
        "name": "Jaunciems",
        "state": "",
        "country": "LV",
        "coord": {
            "lon": 24.174129,
            "lat": 57.039101
        }
    },
    {
        "id": 459563,
        "name": "Inčukalns",
        "state": "",
        "country": "LV",
        "coord": {
            "lon": 24.68639,
            "lat": 57.098061
        }
    },
    {
        "id": 459586,
        "name": "Ilūkste",
        "state": "",
        "country": "LV",
        "coord": {
            "lon": 26.296551,
            "lat": 55.977539
        }
    },
    {
        "id": 459598,
        "name": "Ikšķile",
        "state": "",
        "country": "LV",
        "coord": {
            "lon": 24.5,
            "lat": 56.833328
        }
    },
    {
        "id": 459616,
        "name": "Ieriķi",
        "state": "",
        "country": "LV",
        "coord": {
            "lon": 25.17363,
            "lat": 57.20385
        }
    },
    {
        "id": 459624,
        "name": "Iecava",
        "state": "",
        "country": "LV",
        "coord": {
            "lon": 24.202221,
            "lat": 56.59861
        }
    },
    {
        "id": 459664,
        "name": "Gulbenes novads",
        "state": "",
        "country": "LV",
        "coord": {
            "lon": 26.66667,
            "lat": 57.166672
        }
    },
    {
        "id": 459668,
        "name": "Gulbene",
        "state": "",
        "country": "LV",
        "coord": {
            "lon": 26.752911,
            "lat": 57.17767
        }
    },
    {
        "id": 459692,
        "name": "Grobiņa",
        "state": "",
        "country": "LV",
        "coord": {
            "lon": 21.16782,
            "lat": 56.53521
        }
    },
    {
        "id": 459718,
        "name": "Gridziņkrūmiņi",
        "state": "",
        "country": "LV",
        "coord": {
            "lon": 25.183331,
            "lat": 56.616669
        }
    },
    {
        "id": 459984,
        "name": "Cibla",
        "state": "",
        "country": "LV",
        "coord": {
            "lon": 27.883329,
            "lat": 56.549999
        }
    },
    {
        "id": 460001,
        "name": "Ērgļi",
        "state": "",
        "country": "LV",
        "coord": {
            "lon": 25.636681,
            "lat": 56.897518
        }
    },
    {
        "id": 460019,
        "name": "Engure",
        "state": "",
        "country": "LV",
        "coord": {
            "lon": 23.225269,
            "lat": 57.16061
        }
    },
    {
        "id": 460112,
        "name": "Dzērves",
        "state": "",
        "country": "LV",
        "coord": {
            "lon": 21.66667,
            "lat": 57.216671
        }
    },
    {
        "id": 460187,
        "name": "Dundaga",
        "state": "",
        "country": "LV",
        "coord": {
            "lon": 22.35,
            "lat": 57.51667
        }
    },
    {
        "id": 460274,
        "name": "Dreiliņi",
        "state": "",
        "country": "LV",
        "coord": {
            "lon": 24.233334,
            "lat": 56.950001
        }
    },
    {
        "id": 460311,
        "name": "Dobeles novads",
        "state": "",
        "country": "LV",
        "coord": {
            "lon": 23.16667,
            "lat": 56.583328
        }
    },
    {
        "id": 460312,
        "name": "Dobele",
        "state": "",
        "country": "LV",
        "coord": {
            "lon": 23.27861,
            "lat": 56.625
        }
    },
    {
        "id": 460410,
        "name": "Daugavpils municipality",
        "state": "",
        "country": "LV",
        "coord": {
            "lon": 26.5,
            "lat": 55.916672
        }
    },
    {
        "id": 460413,
        "name": "Daugavpils",
        "state": "",
        "country": "LV",
        "coord": {
            "lon": 26.533331,
            "lat": 55.883331
        }
    },
    {
        "id": 460416,
        "name": "Daugavgrīva",
        "state": "",
        "country": "LV",
        "coord": {
            "lon": 24.036131,
            "lat": 57.043152
        }
    },
    {
        "id": 460474,
        "name": "Dagda",
        "state": "",
        "country": "LV",
        "coord": {
            "lon": 27.53723,
            "lat": 56.095119
        }
    },
    {
        "id": 460540,
        "name": "Cimdenieki",
        "state": "",
        "country": "LV",
        "coord": {
            "lon": 21.116671,
            "lat": 56.533329
        }
    },
    {
        "id": 460568,
        "name": "Cesvaine",
        "state": "",
        "country": "LV",
        "coord": {
            "lon": 26.316669,
            "lat": 56.966671
        }
    },
    {
        "id": 460569,
        "name": "Cēsu Novads",
        "state": "",
        "country": "LV",
        "coord": {
            "lon": 25.5,
            "lat": 57.25
        }
    },
    {
        "id": 460570,
        "name": "Cēsis",
        "state": "",
        "country": "LV",
        "coord": {
            "lon": 25.274561,
            "lat": 57.311878
        }
    },
    {
        "id": 460659,
        "name": "Carnikava",
        "state": "",
        "country": "LV",
        "coord": {
            "lon": 24.274441,
            "lat": 57.12944
        }
    },
    {
        "id": 460786,
        "name": "Brocēni",
        "state": "",
        "country": "LV",
        "coord": {
            "lon": 22.533331,
            "lat": 56.700001
        }
    },
    {
        "id": 460885,
        "name": "Bolderaja",
        "state": "",
        "country": "LV",
        "coord": {
            "lon": 24.05571,
            "lat": 57.031319
        }
    },
    {
        "id": 461112,
        "name": "Bauskas Novads",
        "state": "",
        "country": "LV",
        "coord": {
            "lon": 24.33333,
            "lat": 56.5
        }
    },
    {
        "id": 461114,
        "name": "Bauska",
        "state": "",
        "country": "LV",
        "coord": {
            "lon": 24.190559,
            "lat": 56.407501
        }
    },
    {
        "id": 461160,
        "name": "Balvu Novads",
        "state": "",
        "country": "LV",
        "coord": {
            "lon": 27.5,
            "lat": 57.083328
        }
    },
    {
        "id": 461163,
        "name": "Balvi",
        "state": "",
        "country": "LV",
        "coord": {
            "lon": 27.265829,
            "lat": 57.131302
        }
    },
    {
        "id": 461180,
        "name": "Baltinava",
        "state": "",
        "country": "LV",
        "coord": {
            "lon": 27.65,
            "lat": 56.950001
        }
    },
    {
        "id": 461205,
        "name": "Baloži",
        "state": "",
        "country": "LV",
        "coord": {
            "lon": 24.04389,
            "lat": 56.847778
        }
    },
    {
        "id": 461224,
        "name": "Baldone",
        "state": "",
        "country": "LV",
        "coord": {
            "lon": 24.39444,
            "lat": 56.742779
        }
    },
    {
        "id": 461225,
        "name": "Vārpas",
        "state": "",
        "country": "LV",
        "coord": {
            "lon": 24.35194,
            "lat": 56.70694
        }
    },
    {
        "id": 461255,
        "name": "Babīte",
        "state": "",
        "country": "LV",
        "coord": {
            "lon": 23.9429,
            "lat": 56.954479
        }
    },
    {
        "id": 461336,
        "name": "Auce",
        "state": "",
        "country": "LV",
        "coord": {
            "lon": 22.90169,
            "lat": 56.459808
        }
    },
    {
        "id": 461442,
        "name": "Ape",
        "state": "",
        "country": "LV",
        "coord": {
            "lon": 26.692909,
            "lat": 57.53928
        }
    },
    {
        "id": 461525,
        "name": "Alūksnes Novads",
        "state": "",
        "country": "LV",
        "coord": {
            "lon": 27.0,
            "lat": 57.416672
        }
    },
    {
        "id": 461528,
        "name": "Alūksne",
        "state": "",
        "country": "LV",
        "coord": {
            "lon": 27.049999,
            "lat": 57.416672
        }
    },
    {
        "id": 461534,
        "name": "Alsunga",
        "state": "",
        "country": "LV",
        "coord": {
            "lon": 21.55938,
            "lat": 56.981941
        }
    },
    {
        "id": 461539,
        "name": "Aloja",
        "state": "",
        "country": "LV",
        "coord": {
            "lon": 24.8825,
            "lat": 57.766941
        }
    },
    {
        "id": 461566,
        "name": "Aknīste",
        "state": "",
        "country": "LV",
        "coord": {
            "lon": 25.747829,
            "lat": 56.161518
        }
    },
    {
        "id": 461602,
        "name": "Aizpute",
        "state": "",
        "country": "LV",
        "coord": {
            "lon": 21.6,
            "lat": 56.716671
        }
    },
    {
        "id": 461613,
        "name": "Aizkraukles novads",
        "state": "",
        "country": "LV",
        "coord": {
            "lon": 25.16667,
            "lat": 56.5
        }
    },
    {
        "id": 461615,
        "name": "Aizkraukle",
        "state": "",
        "country": "LV",
        "coord": {
            "lon": 25.255341,
            "lat": 56.604771
        }
    },
    {
        "id": 461628,
        "name": "Ainaži",
        "state": "",
        "country": "LV",
        "coord": {
            "lon": 24.35778,
            "lat": 57.863609
        }
    },
    {
        "id": 461631,
        "name": "Aglona",
        "state": "",
        "country": "LV",
        "coord": {
            "lon": 27.01667,
            "lat": 56.133331
        }
    },
    {
        "id": 461650,
        "name": "Ādaži",
        "state": "",
        "country": "LV",
        "coord": {
            "lon": 24.32139,
            "lat": 57.075829
        }
    },
    {
        "id": 864721,
        "name": "Baloži",
        "state": "",
        "country": "LV",
        "coord": {
            "lon": 24.11861,
            "lat": 56.87611
        }
    },
    {
        "id": 864723,
        "name": "Mārupe",
        "state": "",
        "country": "LV",
        "coord": {
            "lon": 24.046667,
            "lat": 56.900276
        }
    },
    {
        "id": 6615326,
        "name": "Vecrīga",
        "state": "",
        "country": "LV",
        "coord": {
            "lon": 24.104179,
            "lat": 56.949661
        }
    },
    {
        "id": 7628298,
        "name": "Dundagas Novads",
        "state": "",
        "country": "LV",
        "coord": {
            "lon": 22.39472,
            "lat": 57.566669
        }
    },
    {
        "id": 7628302,
        "name": "Rucavas Novads",
        "state": "",
        "country": "LV",
        "coord": {
            "lon": 21.209721,
            "lat": 56.21167
        }
    },
    {
        "id": 7628303,
        "name": "Grobiņas Novads",
        "state": "",
        "country": "LV",
        "coord": {
            "lon": 21.235559,
            "lat": 56.486938
        }
    },
    {
        "id": 7628304,
        "name": "Durbes Novads",
        "state": "",
        "country": "LV",
        "coord": {
            "lon": 21.395281,
            "lat": 56.607498
        }
    },
    {
        "id": 7628305,
        "name": "Aizputes Novads",
        "state": "",
        "country": "LV",
        "coord": {
            "lon": 21.56889,
            "lat": 56.716671
        }
    },
    {
        "id": 7628308,
        "name": "Skrundas Novads",
        "state": "",
        "country": "LV",
        "coord": {
            "lon": 21.98889,
            "lat": 56.66111
        }
    },
    {
        "id": 7628309,
        "name": "Brocēnu Novads",
        "state": "",
        "country": "LV",
        "coord": {
            "lon": 22.65667,
            "lat": 56.714169
        }
    },
    {
        "id": 7628316,
        "name": "Ozolnieku Novads",
        "state": "",
        "country": "LV",
        "coord": {
            "lon": 23.928061,
            "lat": 56.65139
        }
    },
    {
        "id": 7628319,
        "name": "Mārupes Novads",
        "state": "",
        "country": "LV",
        "coord": {
            "lon": 23.958891,
            "lat": 56.886391
        }
    },
    {
        "id": 7628320,
        "name": "Olaines Novads",
        "state": "",
        "country": "LV",
        "coord": {
            "lon": 23.948059,
            "lat": 56.791389
        }
    },
    {
        "id": 7628321,
        "name": "Iecavas Novads",
        "state": "",
        "country": "LV",
        "coord": {
            "lon": 24.206671,
            "lat": 56.60944
        }
    },
    {
        "id": 7628324,
        "name": "Baldones Novads",
        "state": "",
        "country": "LV",
        "coord": {
            "lon": 24.372499,
            "lat": 56.73111
        }
    },
    {
        "id": 7628326,
        "name": "Carnikavas Novads",
        "state": "",
        "country": "LV",
        "coord": {
            "lon": 24.245831,
            "lat": 57.117222
        }
    },
    {
        "id": 7628333,
        "name": "Jaunjelgavas Novads",
        "state": "",
        "country": "LV",
        "coord": {
            "lon": 25.29583,
            "lat": 56.514172
        }
    },
    {
        "id": 7628339,
        "name": "Ilūkstes Novads",
        "state": "",
        "country": "LV",
        "coord": {
            "lon": 26.148331,
            "lat": 56.011669
        }
    },
    {
        "id": 7628345,
        "name": "Aglonas Novads",
        "state": "",
        "country": "LV",
        "coord": {
            "lon": 27.100559,
            "lat": 56.10667
        }
    },
    {
        "id": 7628353,
        "name": "Cesvaines Novads",
        "state": "",
        "country": "LV",
        "coord": {
            "lon": 26.27667,
            "lat": 57.0075
        }
    },
    {
        "id": 7628354,
        "name": "Lubānas Novads",
        "state": "",
        "country": "LV",
        "coord": {
            "lon": 26.735559,
            "lat": 56.927502
        }
    },
    {
        "id": 7628357,
        "name": "Kokneses Novads",
        "state": "",
        "country": "LV",
        "coord": {
            "lon": 25.463329,
            "lat": 56.710281
        }
    },
    {
        "id": 7628358,
        "name": "Ikšķiles Novads",
        "state": "",
        "country": "LV",
        "coord": {
            "lon": 24.583611,
            "lat": 56.860279
        }
    },
    {
        "id": 7628360,
        "name": "Inčukalna Novads",
        "state": "",
        "country": "LV",
        "coord": {
            "lon": 24.650829,
            "lat": 57.102219
        }
    },
    {
        "id": 7628362,
        "name": "Siguldas Novads",
        "state": "",
        "country": "LV",
        "coord": {
            "lon": 24.86389,
            "lat": 57.129719
        }
    },
    {
        "id": 7628364,
        "name": "Mālpils Novads",
        "state": "",
        "country": "LV",
        "coord": {
            "lon": 24.973061,
            "lat": 56.994438
        }
    },
    {
        "id": 7628367,
        "name": "Salacgrīvas Novads",
        "state": "",
        "country": "LV",
        "coord": {
            "lon": 24.451941,
            "lat": 57.74028
        }
    },
    {
        "id": 7628368,
        "name": "Alojas Novads",
        "state": "",
        "country": "LV",
        "coord": {
            "lon": 24.835279,
            "lat": 57.800831
        }
    },
    {
        "id": 7628378,
        "name": "Strenču Novads",
        "state": "",
        "country": "LV",
        "coord": {
            "lon": 25.78306,
            "lat": 57.62611
        }
    },
    {
        "id": 7628381,
        "name": "Jaunpiebalgas Novads",
        "state": "",
        "country": "LV",
        "coord": {
            "lon": 25.97361,
            "lat": 57.150002
        }
    }
]
